datamart_geo/__init__.py
datamart_geo/__main__.py
datamart_geo/main.py
datamart_geo-0.3.1.dist-info/LICENSE.txt
datamart_geo-0.3.1.dist-info/METADATA
datamart_geo-0.3.1.dist-info/WHEEL
datamart_geo-0.3.1.dist-info/top_level.txt
datamart_geo-0.3.1.dist-info/RECORD
