Metadata-Version: 2.1
Name: datamart-geo
Version: 0.3.1
Summary: Geographical location data
Home-page: https://gitlab.com/ViDA-NYU/auctus/datamart-geo
Author: Remi Rampin
Author-email: remi.rampin@nyu.edu
Maintainer: Remi Rampin
Maintainer-email: remi.rampin@nyu.edu
License: BSD-3-Clause
Project-URL: Homepage, https://gitlab.com/ViDA-NYU/auctus/datamart-geo
Project-URL: Source, https://gitlab.com/ViDA-NYU/auctus/datamart-geo
Project-URL: Tracker, https://gitlab.com/ViDA-NYU/auctus/datamart-geo/-/issues
Keywords: auctus,datamart
Platform: UNKNOWN
Classifier: Development Status :: 4 - Beta
Classifier: Intended Audience :: Science/Research
Classifier: License :: Free for non-commercial use
Classifier: Natural Language :: English
Classifier: Operating System :: OS Independent
Classifier: Programming Language :: Python :: 3 :: Only
Classifier: Topic :: Database
Provides-Extra: fuzzy
